LICENSE
README.md
setup.py
asyncmrws/__init__.py
asyncmrws/client.py
asyncmrws/errors.py
asyncmrws/parser.py
asyncmrws.egg-info/PKG-INFO
asyncmrws.egg-info/SOURCES.txt
asyncmrws.egg-info/dependency_links.txt
asyncmrws.egg-info/top_level.txt
asyncmrws.egg-info/zip-safe